climateforcing/__init__.py
climateforcing/_version.py
climateforcing/constants.py
climateforcing/aprp/__init__.py
climateforcing/aprp/aprp.py
climateforcing/atmos/__init__.py
climateforcing/atmos/humidity.py
climateforcing/geometry/__init__.py
climateforcing/solar/__init__.py
climateforcing/solar/orbital_constants.py
climateforcing/solar/solar_position.py
climateforcing/twolayermodel/__init__.py
climateforcing/utci/__init__.py
climateforcing/utci/tmrt.py
climateforcing/utci/utci.py
climateforcing/utils/__init__.py
climateforcing-0.3.0.dist-info/LICENSE
climateforcing-0.3.0.dist-info/METADATA
climateforcing-0.3.0.dist-info/WHEEL
climateforcing-0.3.0.dist-info/top_level.txt
climateforcing-0.3.0.dist-info/RECORD
