Metadata-Version: 2.1
Name: climateforcing
Version: 0.3.0
Summary: Climate-related tools that I use in my work, gathered in a single module
Home-page: https://github.com/chrisroadmap/climateforcing
Author: Chris Smith
Author-email: c.j.smith1@leeds.ac.uk
License: 3-Clause BSD License
Keywords: climate,tools
Platform: UNKNOWN
Classifier: Development Status :: 4 - Beta
Classifier: License :: OSI Approved :: BSD License
Classifier: Intended Audience :: Developers
Classifier: Operating System :: OS Independent
Classifier: Programming Language :: Python :: 3.7
Classifier: Programming Language :: Python :: 3.8
Classifier: Programming Language :: Python :: 3.9
Classifier: Programming Language :: Python :: 3.10
Classifier: Programming Language :: Python :: 3.11
Requires-Dist: cftime (>=1.4.0)
Requires-Dist: numpy
Requires-Dist: netCDF4
Requires-Dist: pandas
Requires-Dist: scipy
Requires-Dist: tqdm
Provides-Extra: deploy
Requires-Dist: twine (>=1.11.0) ; extra == 'deploy'
Requires-Dist: setuptools (>=41.2) ; extra == 'deploy'
Requires-Dist: wheel (>=0.31.0) ; extra == 'deploy'
Provides-Extra: dev
Requires-Dist: black ; extra == 'dev'
Requires-Dist: flake8 ; extra == 'dev'
Requires-Dist: isort ; extra == 'dev'
Requires-Dist: pydocstyle ; extra == 'dev'
Requires-Dist: pylint ; extra == 'dev'
Requires-Dist: readme-renderer ; extra == 'dev'
Requires-Dist: twine (>=1.11.0) ; extra == 'dev'
Requires-Dist: setuptools (>=41.2) ; extra == 'dev'
Requires-Dist: wheel (>=0.31.0) ; extra == 'dev'
Requires-Dist: sphinx (>=1.4) ; extra == 'dev'
Requires-Dist: sphinx-rtd-theme ; extra == 'dev'
Requires-Dist: codecov ; extra == 'dev'
Requires-Dist: coverage ; extra == 'dev'
Requires-Dist: pytest-cov ; extra == 'dev'
Requires-Dist: pytest (>=4.0) ; extra == 'dev'
Provides-Extra: docs
Requires-Dist: sphinx (>=1.4) ; extra == 'docs'
Requires-Dist: sphinx-rtd-theme ; extra == 'docs'
Provides-Extra: tests
Requires-Dist: codecov ; extra == 'tests'
Requires-Dist: coverage ; extra == 'tests'
Requires-Dist: pytest-cov ; extra == 'tests'
Requires-Dist: pytest (>=4.0) ; extra == 'tests'
